pybnesian/__init__.cp312-win_amd64.pyd
pybnesian-0.5.1.dist-info/METADATA
pybnesian-0.5.1.dist-info/WHEEL
pybnesian-0.5.1.dist-info/licenses/LICENSE
pybnesian-0.5.1.dist-info/RECORD
