Metadata-Version: 2.1
Name: pybnesian
Version: 0.5.1
Summary: PyBNesian is a Python package that implements Bayesian networks.
Home-page: https://github.com/davenza/PyBNesian
Author-Email: David Atienza <datienza@fi.upm.es>
License: Copyright 2020 David Atienza
Classifier: Programming Language :: Python :: 3
Classifier: Programming Language :: C++
Classifier: License :: OSI Approved :: MIT License
Classifier: Operating System :: OS Independent
Classifier: Topic :: Scientific/Engineering :: Artificial Intelligence
Project-URL: Homepage, https://github.com/davenza/PyBNesian
Project-URL: Documentation, https://pybnesian.readthedocs.io/en/latest/?badge=latest
Project-URL: Changelog, https://pybnesian.readthedocs.io/en/latest/changelog.html
Requires-Python: >=3.8
Requires-Dist: pybind11>=2.6
Requires-Dist: pyarrow>=14
Requires-Dist: numpy
